{
  "id": 3539735,
  "seasonId": 3525269,
  "round": 10,
  "name": "10. May West Social Day - Stony Creek",
  "date": "2026-05-03",
  "courseName": "Stony Creek Social Days",
  "courseId": "41497",
  "holeCount": 18,
  "par": 56,
  "tracks": [
    {
      "number": "1",
      "par": 3
    },
    {
      "number": "2",
      "par": 3
    },
    {
      "number": "3",
      "par": 3
    },
    {
      "number": "4",
      "par": 4
    },
    {
      "number": "5",
      "par": 3
    },
    {
      "number": "6",
      "par": 3
    },
    {
      "number": "7",
      "par": 3
    },
    {
      "number": "8",
      "par": 3
    },
    {
      "number": "9",
      "par": 3
    },
    {
      "number": "10",
      "par": 3
    },
    {
      "number": "11",
      "par": 3
    },
    {
      "number": "12",
      "par": 3
    },
    {
      "number": "13",
      "par": 4
    },
    {
      "number": "14",
      "par": 3
    },
    {
      "number": "15",
      "par": 3
    },
    {
      "number": "16",
      "par": 3
    },
    {
      "number": "17",
      "par": 3
    },
    {
      "number": "18",
      "par": 3
    }
  ],
  "divisions": [
    {
      "letter": "A",
      "name": "Div A - Metrix Rating > 890",
      "players": [
        {
          "userId": "232102",
          "name": "Hamish Clarkson",
          "group": "10",
          "division": "A",
          "divisionName": "Div A - Metrix Rating > 890",
          "rating": 910,
          "holes": [
            2,
            3,
            2,
            3,
            4,
            3,
            3,
            3,
            3,
            4,
            2,
            2,
            4,
            2,
            2,
            2,
            3,
            3
          ],
          "sum": 50,
          "diff": -6,
          "hc": 7.5,
          "net": 42.5,
          "place": 1
        },
        {
          "userId": "168308",
          "name": "Pen Liu",
          "group": "1",
          "division": "A",
          "divisionName": "Div A - Metrix Rating > 890",
          "rating": 958,
          "holes": [
            2,
            3,
            3,
            3,
            3,
            2,
            3,
            3,
            2,
            2,
            2,
            2,
            4,
            3,
            3,
            4,
            3,
            4
          ],
          "sum": 51,
          "diff": -5,
          "hc": 3.5,
          "net": 47.5,
          "place": 2
        },
        {
          "userId": "133657",
          "name": "Mike Van der Linden",
          "group": "2",
          "division": "A",
          "divisionName": "Div A - Metrix Rating > 890",
          "rating": 896,
          "holes": [
            3,
            3,
            3,
            4,
            2,
            2,
            3,
            2,
            3,
            3,
            3,
            3,
            4,
            5,
            2,
            3,
            3,
            3
          ],
          "sum": 54,
          "diff": -2,
          "hc": 8.67,
          "net": 45.33,
          "place": 5
        },
        {
          "userId": "82834",
          "name": "Mark Hardy",
          "group": "6",
          "division": "A",
          "divisionName": "Div A - Metrix Rating > 890",
          "rating": 920,
          "holes": [
            5,
            3,
            2,
            4,
            3,
            3,
            3,
            3,
            3,
            3,
            2,
            3,
            4,
            3,
            2,
            3,
            2,
            3
          ],
          "sum": 54,
          "diff": -2,
          "hc": 6.67,
          "net": 47.33,
          "place": 5
        },
        {
          "userId": "116370",
          "name": "Tim Ware",
          "group": "14",
          "division": "A",
          "divisionName": "Div A - Metrix Rating > 890",
          "rating": 924,
          "holes": [
            3,
            4,
            3,
            4,
            3,
            2,
            3,
            4,
            2,
            2,
            3,
            2,
            3,
            4,
            2,
            3,
            5,
            3
          ],
          "sum": 55,
          "diff": -1,
          "hc": 6.33,
          "net": 48.67,
          "place": 9
        },
        {
          "userId": "216521",
          "name": "Zach Schloeffel",
          "group": "12",
          "division": "A",
          "divisionName": "Div A - Metrix Rating > 890",
          "rating": 901,
          "holes": [
            3,
            3,
            3,
            3,
            3,
            2,
            3,
            4,
            3,
            5,
            3,
            3,
            4,
            3,
            3,
            3,
            2,
            3
          ],
          "sum": 56,
          "diff": 0,
          "hc": 8.25,
          "net": 47.75,
          "place": 11
        },
        {
          "userId": "211228",
          "name": "Marcus Davies",
          "group": "7",
          "division": "A",
          "divisionName": "Div A - Metrix Rating > 890",
          "rating": 917,
          "holes": [
            3,
            3,
            3,
            3,
            3,
            3,
            3,
            4,
            2,
            3,
            3,
            3,
            4,
            4,
            3,
            3,
            3,
            3
          ],
          "sum": 56,
          "diff": 0,
          "hc": 6.92,
          "net": 49.08,
          "place": 11
        },
        {
          "userId": "141776",
          "name": "Lachlan McKenzie",
          "group": "14",
          "division": "A",
          "divisionName": "Div A - Metrix Rating > 890",
          "rating": 922,
          "holes": [
            2,
            2,
            4,
            4,
            2,
            4,
            2,
            4,
            4,
            2,
            3,
            2,
            4,
            5,
            3,
            3,
            3,
            3
          ],
          "sum": 56,
          "diff": 0,
          "hc": 6.5,
          "net": 49.5,
          "place": 11
        },
        {
          "userId": "180459",
          "name": "Zsolt Csatlos",
          "group": "16",
          "division": "A",
          "divisionName": "Div A - Metrix Rating > 890",
          "rating": 895,
          "holes": [
            3,
            3,
            2,
            4,
            4,
            4,
            3,
            3,
            3,
            3,
            2,
            2,
            4,
            3,
            4,
            3,
            4,
            4
          ],
          "sum": 58,
          "diff": 2,
          "hc": 8.75,
          "net": 49.25,
          "place": 18
        }
      ]
    },
    {
      "letter": "B",
      "name": "Div B - Metrix Rating 845-890",
      "players": [
        {
          "userId": "40476",
          "name": "Succulent Chinese Meal",
          "group": "7",
          "division": "B",
          "divisionName": "Div B - Metrix Rating 845-890",
          "rating": 890,
          "holes": [
            2,
            3,
            2,
            4,
            3,
            3,
            3,
            3,
            3,
            3,
            3,
            2,
            4,
            3,
            3,
            4,
            2,
            3
          ],
          "sum": 53,
          "diff": -3,
          "hc": 9.17,
          "net": 43.83,
          "place": 3
        },
        {
          "userId": "133762",
          "name": "Simon Farrar",
          "group": "7",
          "division": "B",
          "divisionName": "Div B - Metrix Rating 845-890",
          "rating": 888,
          "holes": [
            2,
            3,
            2,
            5,
            3,
            3,
            3,
            3,
            2,
            2,
            2,
            2,
            5,
            4,
            5,
            3,
            3,
            2
          ],
          "sum": 54,
          "diff": -2,
          "hc": 9.33,
          "net": 44.67,
          "place": 5
        },
        {
          "userId": "136105",
          "name": "Mat Daniels",
          "group": "4",
          "division": "B",
          "divisionName": "Div B - Metrix Rating 845-890",
          "rating": 865,
          "holes": [
            3,
            3,
            3,
            3,
            3,
            2,
            3,
            4,
            3,
            2,
            3,
            3,
            4,
            3,
            3,
            4,
            3,
            3
          ],
          "sum": 55,
          "diff": -1,
          "hc": 11.25,
          "net": 43.75,
          "place": 9
        },
        {
          "userId": "116375",
          "name": "Mark Green",
          "group": "4",
          "division": "B",
          "divisionName": "Div B - Metrix Rating 845-890",
          "rating": 872,
          "holes": [
            3,
            3,
            3,
            3,
            3,
            2,
            3,
            4,
            2,
            4,
            3,
            4,
            4,
            4,
            4,
            3,
            2,
            3
          ],
          "sum": 57,
          "diff": 1,
          "hc": 10.67,
          "net": 46.33,
          "place": 14
        },
        {
          "userId": "49416",
          "name": "Patrick Utri",
          "group": "14",
          "division": "B",
          "divisionName": "Div B - Metrix Rating 845-890",
          "rating": 876,
          "holes": [
            3,
            3,
            3,
            4,
            2,
            5,
            3,
            3,
            2,
            2,
            3,
            3,
            5,
            3,
            3,
            4,
            3,
            3
          ],
          "sum": 57,
          "diff": 1,
          "hc": 10.33,
          "net": 46.67,
          "place": 14
        },
        {
          "userId": "185515",
          "name": "Carlton Klerck",
          "group": "3",
          "division": "B",
          "divisionName": "Div B - Metrix Rating 845-890",
          "rating": 880,
          "holes": [
            3,
            5,
            2,
            3,
            3,
            3,
            3,
            3,
            3,
            3,
            3,
            4,
            5,
            4,
            5,
            3,
            3,
            2
          ],
          "sum": 60,
          "diff": 4,
          "hc": 10,
          "net": 50,
          "place": 21
        },
        {
          "userId": "182547",
          "name": "Choo Tran",
          "group": "1",
          "division": "B",
          "divisionName": "Div B - Metrix Rating 845-890",
          "rating": 886,
          "holes": [
            2,
            5,
            3,
            4,
            4,
            3,
            3,
            3,
            2,
            3,
            3,
            2,
            4,
            3,
            4,
            5,
            3,
            4
          ],
          "sum": 60,
          "diff": 4,
          "hc": 9.5,
          "net": 50.5,
          "place": 21
        },
        {
          "userId": "135324",
          "name": "Curt Moulton",
          "group": "16",
          "division": "B",
          "divisionName": "Div B - Metrix Rating 845-890",
          "rating": 848,
          "holes": [
            2,
            3,
            2,
            4,
            3,
            3,
            3,
            3,
            3,
            6,
            3,
            5,
            4,
            3,
            3,
            5,
            3,
            3
          ],
          "sum": 61,
          "diff": 5,
          "hc": 12.67,
          "net": 48.33,
          "place": 24
        },
        {
          "userId": "211227",
          "name": "Ross Davies",
          "group": "8",
          "division": "B",
          "divisionName": "Div B - Metrix Rating 845-890",
          "rating": 865,
          "holes": [
            4,
            4,
            3,
            3,
            3,
            4,
            6,
            4,
            3,
            4,
            2,
            3,
            4,
            3,
            2,
            4,
            3,
            3
          ],
          "sum": 62,
          "diff": 6,
          "hc": 11.25,
          "net": 50.75,
          "place": 26
        },
        {
          "userId": "194910",
          "name": "Glen Ralston",
          "group": "3",
          "division": "B",
          "divisionName": "Div B - Metrix Rating 845-890",
          "rating": 883,
          "holes": [
            5,
            4,
            3,
            4,
            3,
            4,
            4,
            4,
            2,
            2,
            3,
            4,
            5,
            3,
            3,
            3,
            3,
            3
          ],
          "sum": 62,
          "diff": 6,
          "hc": 9.75,
          "net": 52.25,
          "place": 26
        },
        {
          "userId": "218039",
          "name": "Simon Mackay",
          "group": "12",
          "division": "B",
          "divisionName": "Div B - Metrix Rating 845-890",
          "rating": 851,
          "holes": [
            3,
            3,
            3,
            5,
            3,
            3,
            3,
            3,
            4,
            4,
            4,
            4,
            6,
            4,
            3,
            3,
            2,
            4
          ],
          "sum": 64,
          "diff": 8,
          "hc": 12.42,
          "net": 51.58,
          "place": 34
        },
        {
          "userId": "170805",
          "name": "Max Tats",
          "group": "14",
          "division": "B",
          "divisionName": "Div B - Metrix Rating 845-890",
          "rating": 865,
          "holes": [
            3,
            2,
            5,
            3,
            4,
            4,
            3,
            5,
            3,
            5,
            3,
            4,
            5,
            4,
            4,
            3,
            3,
            5
          ],
          "sum": 68,
          "diff": 12,
          "hc": 11.25,
          "net": 56.75,
          "place": 38
        }
      ]
    },
    {
      "letter": "C",
      "name": "Div C - Metrix Rating 790-845",
      "players": [
        {
          "userId": "224659",
          "name": "Daniel Santamaria",
          "group": "9",
          "division": "C",
          "divisionName": "Div C - Metrix Rating 790-845",
          "rating": 845,
          "holes": [
            2,
            3,
            2,
            3,
            2,
            3,
            2,
            3,
            3,
            3,
            3,
            4,
            4,
            4,
            3,
            3,
            2,
            4
          ],
          "sum": 53,
          "diff": -3,
          "hc": 12.92,
          "net": 40.08,
          "place": 3
        },
        {
          "userId": "132835",
          "name": "Illia Kravchenko",
          "group": "9",
          "division": "C",
          "divisionName": "Div C - Metrix Rating 790-845",
          "rating": 815,
          "holes": [
            3,
            3,
            3,
            4,
            3,
            3,
            4,
            4,
            3,
            2,
            3,
            3,
            4,
            3,
            3,
            4,
            2,
            3
          ],
          "sum": 57,
          "diff": 1,
          "hc": 15.42,
          "net": 41.58,
          "place": 14
        },
        {
          "userId": "99466",
          "name": "Robert Lambert",
          "group": "1",
          "division": "C",
          "divisionName": "Div C - Metrix Rating 790-845",
          "rating": 836,
          "holes": [
            3,
            4,
            3,
            4,
            3,
            3,
            3,
            2,
            3,
            2,
            4,
            2,
            4,
            3,
            3,
            4,
            3,
            4
          ],
          "sum": 57,
          "diff": 1,
          "hc": 13.67,
          "net": 43.33,
          "place": 14
        },
        {
          "userId": "113708",
          "name": "Aaron Ponnudurai",
          "group": "3",
          "division": "C",
          "divisionName": "Div C - Metrix Rating 790-845",
          "rating": 817,
          "holes": [
            4,
            4,
            2,
            4,
            3,
            2,
            5,
            3,
            3,
            3,
            3,
            3,
            4,
            3,
            3,
            3,
            3,
            3
          ],
          "sum": 58,
          "diff": 2,
          "hc": 15.25,
          "net": 42.75,
          "place": 18
        },
        {
          "userId": "168204",
          "name": "David Wood",
          "group": "5",
          "division": "C",
          "divisionName": "Div C - Metrix Rating 790-845",
          "rating": 835,
          "holes": [
            5,
            3,
            2,
            4,
            5,
            3,
            3,
            3,
            3,
            3,
            2,
            3,
            5,
            4,
            3,
            3,
            2,
            2
          ],
          "sum": 58,
          "diff": 2,
          "hc": 13.75,
          "net": 44.25,
          "place": 18
        },
        {
          "userId": "134912",
          "name": "Eamon Dawson",
          "group": "12",
          "division": "C",
          "divisionName": "Div C - Metrix Rating 790-845",
          "rating": 843,
          "holes": [
            3,
            5,
            2,
            4,
            3,
            3,
            3,
            3,
            3,
            2,
            5,
            3,
            4,
            5,
            3,
            3,
            3,
            3
          ],
          "sum": 60,
          "diff": 4,
          "hc": 13.08,
          "net": 46.92,
          "place": 21
        },
        {
          "userId": "146571",
          "name": "Albie Cunningham",
          "group": "5",
          "division": "C",
          "divisionName": "Div C - Metrix Rating 790-845",
          "rating": 838,
          "holes": [
            2,
            3,
            2,
            3,
            4,
            3,
            5,
            4,
            3,
            3,
            3,
            5,
            4,
            6,
            3,
            3,
            3,
            3
          ],
          "sum": 62,
          "diff": 6,
          "hc": 13.5,
          "net": 48.5,
          "place": 26
        },
        {
          "userId": "40487",
          "name": "Emma Winkworth",
          "group": "10",
          "division": "C",
          "divisionName": "Div C - Metrix Rating 790-845",
          "rating": 799,
          "holes": [
            2,
            4,
            3,
            4,
            3,
            3,
            4,
            4,
            4,
            2,
            3,
            4,
            5,
            5,
            3,
            3,
            4,
            3
          ],
          "sum": 63,
          "diff": 7,
          "hc": 16.75,
          "net": 46.25,
          "place": 30
        },
        {
          "userId": "130554",
          "name": "PETER HOWES",
          "group": "9",
          "division": "C",
          "divisionName": "Div C - Metrix Rating 790-845",
          "rating": 804,
          "holes": [
            2,
            3,
            4,
            5,
            3,
            2,
            4,
            3,
            4,
            4,
            3,
            3,
            5,
            6,
            3,
            4,
            2,
            3
          ],
          "sum": 63,
          "diff": 7,
          "hc": 16.33,
          "net": 46.67,
          "place": 30
        },
        {
          "userId": "137014",
          "name": "Phillip Hall",
          "group": "12",
          "division": "C",
          "divisionName": "Div C - Metrix Rating 790-845",
          "rating": 839,
          "holes": [
            6,
            3,
            2,
            4,
            2,
            4,
            3,
            4,
            3,
            5,
            3,
            3,
            4,
            5,
            3,
            4,
            2,
            3
          ],
          "sum": 63,
          "diff": 7,
          "hc": 13.42,
          "net": 49.58,
          "place": 30
        },
        {
          "userId": "136103",
          "name": "Kim Michell",
          "group": "4",
          "division": "C",
          "divisionName": "Div C - Metrix Rating 790-845",
          "rating": 807,
          "holes": [
            3,
            3,
            4,
            4,
            3,
            3,
            4,
            4,
            3,
            4,
            3,
            3,
            5,
            5,
            4,
            5,
            3,
            3
          ],
          "sum": 66,
          "diff": 10,
          "hc": 16.08,
          "net": 49.92,
          "place": 37
        }
      ]
    },
    {
      "letter": "D",
      "name": "Div D - Metrix Rating <790",
      "players": [
        {
          "userId": "218202",
          "name": "Rhys Vieusseux",
          "group": "2",
          "division": "D",
          "divisionName": "Div D - Metrix Rating <790",
          "rating": 760,
          "holes": [
            4,
            3,
            4,
            4,
            4,
            3,
            3,
            2,
            3,
            3,
            3,
            3,
            6,
            4,
            3,
            3,
            2,
            4
          ],
          "sum": 61,
          "diff": 5,
          "hc": 20,
          "net": 41,
          "place": 24
        },
        {
          "userId": "227859",
          "name": "William Wong",
          "group": "9",
          "division": "D",
          "divisionName": "Div D - Metrix Rating <790",
          "rating": 762,
          "holes": [
            4,
            3,
            3,
            4,
            3,
            2,
            4,
            3,
            5,
            3,
            4,
            3,
            4,
            4,
            3,
            6,
            2,
            3
          ],
          "sum": 63,
          "diff": 7,
          "hc": 19.83,
          "net": 43.17,
          "place": 30
        },
        {
          "userId": "188623",
          "name": "John Baker",
          "group": "8",
          "division": "D",
          "divisionName": "Div D - Metrix Rating <790",
          "rating": 769,
          "holes": [
            3,
            3,
            3,
            4,
            4,
            2,
            3,
            4,
            3,
            4,
            3,
            3,
            6,
            4,
            5,
            4,
            3,
            3
          ],
          "sum": 64,
          "diff": 8,
          "hc": 19.25,
          "net": 44.75,
          "place": 34
        },
        {
          "userId": "217431",
          "name": "Luis Saavedra",
          "group": "5",
          "division": "D",
          "divisionName": "Div D - Metrix Rating <790",
          "rating": 754,
          "holes": [
            3,
            4,
            4,
            5,
            3,
            4,
            3,
            4,
            3,
            3,
            3,
            3,
            5,
            5,
            4,
            4,
            2,
            3
          ],
          "sum": 65,
          "diff": 9,
          "hc": 20.5,
          "net": 44.5,
          "place": 36
        },
        {
          "userId": "218492",
          "name": "Mike Vieusseux",
          "group": "2",
          "division": "D",
          "divisionName": "Div D - Metrix Rating <790",
          "rating": 736,
          "holes": [
            4,
            4,
            2,
            4,
            3,
            3,
            4,
            3,
            3,
            3,
            4,
            6,
            5,
            4,
            3,
            4,
            4,
            5
          ],
          "sum": 68,
          "diff": 12,
          "hc": 22,
          "net": 46,
          "place": 38
        },
        {
          "userId": "234783",
          "name": "James Elliott",
          "group": "16",
          "division": "D",
          "divisionName": "Div D - Metrix Rating <790",
          "rating": 747,
          "holes": [
            4,
            4,
            4,
            6,
            3,
            3,
            3,
            4,
            4,
            4,
            3,
            3,
            5,
            4,
            4,
            4,
            3,
            4
          ],
          "sum": 69,
          "diff": 13,
          "hc": 21.08,
          "net": 47.92,
          "place": 40
        },
        {
          "userId": "79684",
          "name": "Aaron DeBuhr",
          "group": "1",
          "division": "D",
          "divisionName": "Div D - Metrix Rating <790",
          "rating": 736,
          "holes": [
            5,
            3,
            4,
            6,
            3,
            3,
            4,
            4,
            3,
            4,
            4,
            3,
            4,
            3,
            4,
            4,
            5,
            4
          ],
          "sum": 70,
          "diff": 14,
          "hc": 22,
          "net": 48,
          "place": 41
        },
        {
          "userId": "217207",
          "name": "Charlotte Davies",
          "group": "8",
          "division": "D",
          "divisionName": "Div D - Metrix Rating <790",
          "rating": 746,
          "holes": [
            4,
            4,
            4,
            5,
            3,
            3,
            5,
            4,
            3,
            5,
            2,
            5,
            5,
            5,
            4,
            4,
            2,
            3
          ],
          "sum": 70,
          "diff": 14,
          "hc": 21.17,
          "net": 48.83,
          "place": 41
        },
        {
          "userId": "216079",
          "name": "Robert Higgins",
          "group": "16",
          "division": "D",
          "divisionName": "Div D - Metrix Rating <790",
          "rating": 635,
          "holes": [
            5,
            3,
            4,
            5,
            3,
            3,
            4,
            4,
            3,
            5,
            3,
            5,
            6,
            3,
            4,
            4,
            4,
            4
          ],
          "sum": 72,
          "diff": 16,
          "hc": 30.42,
          "net": 41.58,
          "place": 43
        },
        {
          "userId": "234876",
          "name": "Parker Clarkson",
          "group": "10",
          "division": "D",
          "divisionName": "Div D - Metrix Rating <790",
          "rating": 786,
          "holes": [
            7,
            5,
            5,
            5,
            5,
            3,
            5,
            3,
            3,
            3,
            5,
            3,
            5,
            3,
            3,
            3,
            3,
            4
          ],
          "sum": 73,
          "diff": 17,
          "hc": 17.83,
          "net": 55.17,
          "place": 44
        },
        {
          "userId": "113704",
          "name": "Michael Smith",
          "group": "8",
          "division": "D",
          "divisionName": "Div D - Metrix Rating <790",
          "rating": 719,
          "holes": [
            6,
            3,
            4,
            8,
            3,
            4,
            4,
            5,
            3,
            4,
            3,
            4,
            7,
            4,
            3,
            4,
            3,
            3
          ],
          "sum": 75,
          "diff": 19,
          "hc": 23.42,
          "net": 51.58,
          "place": 45
        },
        {
          "userId": "235235",
          "name": "Rafal Wadowski",
          "group": "10",
          "division": "D",
          "divisionName": "Div D - Metrix Rating <790",
          "rating": 677,
          "holes": [
            4,
            4,
            5,
            6,
            4,
            3,
            4,
            5,
            6,
            3,
            5,
            4,
            5,
            5,
            4,
            4,
            5,
            4
          ],
          "sum": 80,
          "diff": 24,
          "hc": 26.92,
          "net": 53.08,
          "place": 47
        },
        {
          "userId": "217150",
          "name": "Mia Daniels",
          "group": "4",
          "division": "D",
          "divisionName": "Div D - Metrix Rating <790",
          "rating": 449,
          "holes": [
            5,
            5,
            5,
            7,
            5,
            5,
            6,
            4,
            5,
            4,
            4,
            3,
            6,
            4,
            5,
            6,
            4,
            5
          ],
          "sum": 88,
          "diff": 32,
          "hc": 45.92,
          "net": 42.08,
          "place": 48
        }
      ]
    },
    {
      "letter": "X",
      "name": "Div X - No Metrix Rating",
      "players": [
        {
          "userId": "194615",
          "name": "Richard Pasquier",
          "group": "5",
          "division": "X",
          "divisionName": "Div X - No Metrix Rating",
          "rating": 0,
          "holes": [
            4,
            4,
            2,
            4,
            3,
            3,
            3,
            3,
            2,
            2,
            2,
            3,
            4,
            2,
            3,
            4,
            2,
            4
          ],
          "sum": 54,
          "diff": -2,
          "hc": 83.33,
          "net": -29.33,
          "place": 5
        },
        {
          "userId": "236835",
          "name": "Ben Quinney",
          "group": "6",
          "division": "X",
          "divisionName": "Div X - No Metrix Rating",
          "rating": 0,
          "holes": [
            4,
            4,
            2,
            4,
            3,
            2,
            3,
            3,
            3,
            4,
            4,
            4,
            4,
            4,
            4,
            4,
            3,
            3
          ],
          "sum": 62,
          "diff": 6,
          "hc": 83.33,
          "net": -21.33,
          "place": 26
        }
      ]
    },
    {
      "letter": "Z",
      "name": "Div Z - Non MDGC Members",
      "players": [
        {
          "userId": "237006",
          "name": "Michael Ranga",
          "group": "6",
          "division": "Z",
          "divisionName": "Div Z - Non MDGC Members",
          "rating": 0,
          "holes": [
            3,
            3,
            4,
            6,
            6,
            5,
            3,
            5,
            3,
            3,
            4,
            3,
            4,
            5,
            5,
            6,
            4,
            3
          ],
          "sum": 75,
          "diff": 19,
          "hc": 83.33,
          "net": -8.33,
          "place": 45
        }
      ]
    }
  ]
}